dpqc/__init__.py
dpqc/classes.py
dpqc-0.0.1.dist-info/licenses/LICENSE
dpqc-0.0.1.dist-info/METADATA
dpqc-0.0.1.dist-info/WHEEL
dpqc-0.0.1.dist-info/top_level.txt
dpqc-0.0.1.dist-info/RECORD
