Metadata-Version: 2.4
Name: dpqc
Version: 0.0.1
Summary: DPQC - Developer's PQC (Post-Quantum Cryptography) Library
Home-page: https://github.com/QudsLab/dpqc
Author: QudsLab
Author-email: QudsLab <QudsLab@proton.me>
License: MIT License
Project-URL: Homepage, https://github.com/QudsLab/dpqc
Project-URL: Repository, https://github.com/QudsLab/dpqc
Project-URL: Issues, https://github.com/QudsLab/dpqc/issues
Keywords: post-quantum,cryptography,pqc,quantum-safe,ml-kem,ml-dsa,falcon
Classifier: Development Status :: 3 - Alpha
Classifier: Intended Audience :: Developers
Classifier: Topic :: Security :: Cryptography
Classifier: License :: OSI Approved :: MIT License
Classifier: Programming Language :: Python :: 3
Classifier: Programming Language :: Python :: 3.7
Classifier: Programming Language :: Python :: 3.8
Classifier: Programming Language :: Python :: 3.9
Classifier: Programming Language :: Python :: 3.10
Classifier: Programming Language :: Python :: 3.11
Classifier: Programming Language :: Python :: 3.12
Classifier: Operating System :: OS Independent
Requires-Python: >=3.7
License-File: LICENSE
Requires-Dist: termcolor>=1.1.0
Dynamic: author
Dynamic: home-page
Dynamic: license-file
Dynamic: requires-python
